[
  {"group":"GRUP LOMBA DIVA4D","comment":"#DIVA4D (GONVA33) = 87*43*06"},
  {"group":"VIP GRUP ALLPAS II","comment":"Tok99Toto ( BLEKEK ) : 87*43*06"},
  {"group":"KEITOGEL EVENT","comment":"#keitogel = (DRESGON65) = 79*50*08"},
  {"group":"UPINSLOT OFFICIAL","comment":"#UPINSLOT (HALALUYE ) 79*50*08 BETTING"},
  {"group":"PEDRO TRIFHTING SHOPS","comment":"#PEDRO4D (DRES02GON*79*50*08)"},
  {"group":"453P VIP","comment":"ASEPTOGEL BLEKETEK 95*14*16"},
  {"group":"VESPA7093L","comment":"VESPATOGEL (GONDRES) 95*14*16"},
  {"group":"Lomba Hoho","comment":"BAKEKOK : 59*29*72 #HOHOTOGEL"},
  {"group":"KAPALSLOT OFFICIAL","comment":"#KAPALSLOT ( TUKMOI44 ) = 59*29*72"},
  {"group":"SAHABAT K86T O T O","comment":"K86TOTO ( MYTH826 ) : 02*49*53"},
  {"group":"BUKU MIMPI 4D","comment":"IYATOTO EMUTNYAK69 02*49*53"},
  {"group":"OPUNG4D","comment":"OPUNG4D ( PINJAM100SU ) : 64*92*94"},
  {"group":"REKAP LOMBA OMASLOT CUAN","comment":"#OMASLOT (ASLUBAD) : 64*92 BETTING"},
  {"group":"NEMO4D GRUP LOMBA","comment":"NEMO4D (DENDENGDU) : 92*94*70"},
  {"group":"LOMBA INA - DUA D","comment":"BLEKEK / 76*12*63 / #inatogel"},
  {"group":"TAFSIR MIMPI","comment":"SIJITOGEL GONDRES 76*12*63"},
  {"group":"LOMBA HAT0R1","comment":"#HATORIBET*BAKEKOK*76*12*63"},
  {"group":"MASTER KUY","comment":"TOGELKUY MONTISS 85*31*91"},
  {"group":"HITO GROUP","comment":"#HITOGEL SUKONS 85*31*91"},
  {"group":"DDP ( NEW )","comment":"NANA65 / 76*12*63 / #inatogel"},
  {"group":"VIDEO LUCUCU","comment":"Sikat terus kak... jangann kasih kendor dor...!"}
]